MANIFEST.in
README.rst
requirements.txt
setup.py
Socks5man.egg-info/PKG-INFO
Socks5man.egg-info/SOURCES.txt
Socks5man.egg-info/dependency_links.txt
Socks5man.egg-info/entry_points.txt
Socks5man.egg-info/requires.txt
Socks5man.egg-info/top_level.txt
socks5man/__init__.py
socks5man/config.py
socks5man/constants.py
socks5man/database.py
socks5man/exceptions.py
socks5man/helpers.py
socks5man/logs.py
socks5man/main.py
socks5man/manager.py
socks5man/misc.py
socks5man/socks5.py
socks5man/tools.py
socks5man/setupdata/conf/socks5man.conf
socks5man/setupdata/db_migration/alembic.ini
socks5man/setupdata/db_migration/env.py
socks5man/setupdata/db_migration/script.py.mako
socks5man/setupdata/db_migration/versions/add_db_schema_versioning.py
socks5man/setupdata/db_migration/versions/add_socks_dns_port.py
socks5man/setupdata/geodb/.version
socks5man/setupdata/geodb/geodblite.tar.gz
socks5man/setupdata/geodb/extracted/.gitignore