Metadata-Version: 1.2
Name: Socks5man
Version: 0.2.0
Summary: SOCKS5 server management tool and library
Home-page: https://github.com/RicoVZ/socks5man
Author: Ricardo van Zutphen
Author-email: ricardo@hatching.io
License: GPLv3
Keywords: socks5man socks5 tester management library verification
Platform: UNKNOWN
Classifier: Development Status :: 3 - Alpha
Classifier: Environment :: Console
Classifier: Framework :: Pytest
Classifier: Intended Audience :: Developers
Classifier: Intended Audience :: Information Technology
Classifier: Intended Audience :: Science/Research
Classifier: Intended Audience :: System Administrators
Classifier: License :: OSI Approved :: GNU General Public License v3 (GPLv3)
Classifier: Natural Language :: English
Classifier: Operating System :: POSIX :: Linux
Classifier: Programming Language :: Python :: 2.7
Classifier: Topic :: Software Development :: Libraries :: Python Modules
Classifier: Topic :: System :: Systems Administration
Classifier: Topic :: System :: Monitoring
Classifier: Topic :: Security
Requires-Python: >=2.7, <3.0
